pylint_quotes/__init__.py
pylint_quotes/__version__.py
pylint_quotes/checker.py
pylint_quotes/plugin.py
pylint_quotes-0.2.3.dist-info/LICENSE
pylint_quotes-0.2.3.dist-info/METADATA
pylint_quotes-0.2.3.dist-info/WHEEL
pylint_quotes-0.2.3.dist-info/top_level.txt
pylint_quotes-0.2.3.dist-info/RECORD
