Metadata-Version: 1.2
Name: pylint-quotes
Version: 0.2.3
Summary: Quote consistency checker for PyLint..
Home-page: https://github.com/edaniszewski/pylint-quotes
Author: Erick Daniszewski
Author-email: edaniszewski@gmail.com
License: MIT
Keywords: pylint linting string quotes
Platform: UNKNOWN
Classifier: Intended Audience :: Developers
Classifier: Natural Language :: English
Classifier: License :: OSI Approved :: MIT License
Classifier: Programming Language :: Python
Classifier: Programming Language :: Python :: 3
Classifier: Programming Language :: Python :: 3.6
Classifier: Programming Language :: Python :: 3.7
Classifier: Programming Language :: Python :: 3.8
Classifier: Programming Language :: Python :: 3.9
Classifier: Topic :: Software Development
Classifier: Topic :: Utilities
Requires-Python: >=3.6
